gmap_scrabbler/__init__.py
gmap_scrabbler/__main__.py
gmap_scrabbler/main.py
gmap_scrabbler/selenium_bundle.py
gmap_scrabbler/selenium_controller.py
gmap_scrabbler/selenium_driver.py
gmap_scrabbler-0.2.2.dist-info/METADATA
gmap_scrabbler-0.2.2.dist-info/WHEEL
gmap_scrabbler-0.2.2.dist-info/top_level.txt
gmap_scrabbler-0.2.2.dist-info/RECORD
