Metadata-Version: 2.1
Name: gmap-scrabbler
Version: 0.2.2
Summary: The Google Map Reviews Web Scrabbler is a specialized tool designed to extract Google Maps reviews to a .CSV file.
Home-page: https://github.com/freezerain/gMaps_selenium_scrabbler
Author: Ilia Rodikov
Author-email: rain-ilia@rambler.ru
Keywords: pypi,cicd,python
Classifier: Development Status :: 1 - Planning
Classifier: Intended Audience :: Developers
Classifier: Programming Language :: Python :: 3
Classifier: Operating System :: Unix
Classifier: Operating System :: MacOS :: MacOS X
Classifier: Operating System :: Microsoft :: Windows
Requires-Dist: numpy
